setup.py
cnareader.egg-info/PKG-INFO
cnareader.egg-info/SOURCES.txt
cnareader.egg-info/dependency_links.txt
cnareader.egg-info/entry_points.txt
cnareader.egg-info/not-zip-safe
cnareader.egg-info/requires.txt
cnareader.egg-info/top_level.txt
src/__init__.py
src/__main__.py
src/back.py
src/front.py
src/classes/__init__.py
src/classes/keystroke.py
src/classes/page.py